hometaxbot/.DS_Store
hometaxbot/__init__.py
hometaxbot/cli.py
hometaxbot/crypto.py
hometaxbot/models.py
hometaxbot/types.py
hometaxbot/scraper/__init__.py
hometaxbot/scraper/hometax_xml_fields.yml
hometaxbot/scraper/reports.py
hometaxbot/scraper/requestutil.py
hometaxbot/scraper/taxagent.py
hometaxbot/scraper/transactions.py
hometaxbot/scraper/util.py
hometaxbot/scraper/webdriver.py
hometaxbot-0.2.20.dist-info/licenses/LICENSE
hometaxbot-0.2.20.dist-info/WHEEL
hometaxbot-0.2.20.dist-info/METADATA
hometaxbot-0.2.20.dist-info/RECORD
