Metadata-Version: 2.4
Name: hometaxbot
Version: 0.2.20
Summary: 홈택스에 로그인해서 여러 가지 정보를 requests로 수집해오는 봇입니다.
Author-email: Pak Youngrok <youngrok@finecode.kr>
Classifier: License :: OSI Approved :: Apache Software License
License-File: LICENSE
Requires-Dist: pypinksign
Requires-Dist: pycryptodome
Requires-Dist: pyOpenSSL
Requires-Dist: python-dateutil
Requires-Dist: pyyaml
Requires-Dist: certifi
Requires-Dist: urllib3
Requires-Dist: idna
Requires-Dist: requests
Requires-Dist: typer
Requires-Dist: httpx[http2]
Project-URL: Home, https://github.com/finecodekr/hometaxbot
